Workbook

Sheet Instrucciones
B1: Registro El Tilichero: fichas, consultas y resumen
B2: Plantilla vacía. Sirve para saber qué video trae pedidos sin guardar datos personales.
B5: Leyenda
B6: Celda amarilla | C6: Se llena a mano.
B7: Celda gris | C7: Se calcula sola. No escribir encima.
B8: Fila roja en «Consultas» | C8: Algo no cuadra en esa fila (ver «Control del registro» en «Resumen»).
B10: Cuándo llenar
B11: Antes de grabar | C11: Hoja «Fichas»: una fila por producto (GAME, RETRO, RGB). Ningún dato entra a un guion hasta que su columna «¿Verificado?» diga Sí.
B12: Cada día | C12: Hoja «Consultas»: una fila por conversación nueva de WhatsApp. El N.º se pone solo al escribir la fecha o el código.
B13: A los 7 días | C13: Hoja «Resumen»: escribí Desde/Hasta, la inversión en pauta de cada código (vacía = sin pauta), el alcance de cada pieza por plataforma (de Insights), las fechas de publicación y el alcance de GAME1 y GAME2 en su ventana, y contestá las preguntas de condiciones. Mandá el resumen a Altiora.
B15: Códigos de pieza
B16: GAME1 y GAME2 | C16: Dos videos distintos del MISMO audífono gaming (se comparan entre sí).
B17: RETRO1 | C17: Video de la consola portátil retro.
B18: RGB1 | C18: Video del mouse o periférico gaming (o del accesorio que lo sustituya).
B19: Regla común | C19: El código dice de qué pieza viene la consulta; el canal dice dónde la vio.
B20: OTRO | C20: Vino por una publicación sin código que sí se identifica: Marketplace, grupo, estado de WhatsApp, clip o anuncio con foto. Se anota con su canal.
B21: SIN CODIGO | C21: No se sabe la pieza: no dijo código ni de qué publicación viene, aunque diga el canal («lo vi en Instagram») o que se lo recomendaron. También si escribió un código que no está en la lista (copialo en la nota). Se anota con su canal: Instagram, Facebook (página), TikTok, Recomendación o No dijo.
B23: Canal de origen
B24: Regla | C24: El canal es dónde vio la publicación por primera vez, no por dónde escribe. Casi todo termina en WhatsApp, pero eso no cambia el canal.
B25: Instagram / TikTok | C25: Vio una publicación, reel, historia o clip sin pagar en esa red.
B26: Facebook (página) | C26: Vio una publicación o reel de la página de El Tilichero, sin pagar.
B27: Facebook Marketplace | C27: Vio la publicación en Marketplace, aunque escriba por Messenger y después pase a WhatsApp. Código: OTRO.
B28: Grupo de Facebook | C28: Vio la publicación en un grupo de compra y venta. Código: OTRO.
B29: Estado de WhatsApp | C29: Vio un estado de WhatsApp del negocio. Código: OTRO.
B30: Anuncio pagado (Meta) | C30: Llegó por un anuncio pagado de Facebook o Instagram, por ejemplo uno de clic a WhatsApp. Código: el de la pieza si el anuncio la usa; si no, OTRO.
B31: Recomendación / Otro / No dijo | C31: Recomendación: se lo recomendó alguien (código SIN CODIGO). Otro: cualquier otro origen. No dijo: no sabe o no contesta (código SIN CODIGO; no insistir).
B33: Alcance (Insights)
B34: Qué anotar | C34: El total de cuentas o personas alcanzadas por cada pieza en cada plataforma, no las reproducciones. Solo el número: nunca nombres de cuentas ni listas de quién la vio.
B35: Dónde verlo | C35: En las estadísticas (Insights) de cada publicación, con cuenta profesional. Instagram: «Cuentas alcanzadas». Facebook (Meta Business Suite): «Alcance». TikTok: el dato de espectadores del video. Los nombres pueden cambiar con la app.
B36: Cuándo leerlo | C36: Cuadro general: el día «Hasta». Prueba A: el día «Cuenta hasta» de cada pieza. El alcance se acumula, así que leerlo otro día cambia el número.
B38: No registrar
B39: Nunca | C39: Nombres, teléfonos, direcciones exactas, correos, capturas de chats ni datos de pago. La zona es solo GAM / Fuera de GAM / No dijo.
B41: Definiciones
B42: Consulta repetida | C42: La misma persona vuelve a escribir por lo mismo: marcá Sí y actualizá la fila original. Las repetidas no se cuentan.
B43: Consulta cualificada | C43: La persona dice qué producto o necesidad tiene Y en qué zona recibe.
B44: Cotizada | C44: Le mandaste precio final con envío.
B45: Pedido confirmado | C45: La persona confirmó que lo compra. Todavía no es plata.
B46: Cobrado | C46: El pago entró. Solo aquí se anota el monto en colones.
B47: Venta neta | C47: Cobrado menos devoluciones y descuentos. No se calcula en este archivo: si hubo devolución, escribí DEVOLUCIÓN y el monto en la nota, sin borrar el cobro.
B49: Cómo leer
B50: NO CALCULABLE | C50: La división no se puede hacer porque abajo hay 0 o nada. No es 0 %.
B51: SIN PAUTA | C51: Ese código no tiene inversión escrita, así que no hay costo por consulta.
B52: Cualificadas / alcance | C52: Solo se calcula con alcance escrito y mayor que 0. Si no, dice NO CALCULABLE y se miran los números absolutos junto al alcance que sí se conoce. Más consultas pueden venir de más alcance y no de un mejor video.
B53: Prueba A | C53: Compara GAME1 y GAME2 con la misma ventana de días desde que se publicó cada uno. Las demás piezas salen en días distintos: no se comparan con el cuadro general.
B54: Producto ganador | C54: Con pocas consultas no se declara ganador. Si hubo falta de stock, cambio de precio o GAME1 y GAME2 salieron en canales u horas distintas, la comparación no vale: se extiende o se repite.
B56: Formatos
B57: Fechas | C57: dd/mm/aaaa. Revisá que el día y el mes queden en su lugar.
B58: Montos | C58: Solo números, en colones, sin el símbolo ₡ (el formato lo pone).
B59: Minutos | C59: Número entero: minutos desde que escribió hasta tu primera respuesta.

Sheet Fichas
A1: Código | B1: Producto | C1: Estado de la ficha | D1: Campos listos (de 16) | E1: 1. Marca | I1: 2. Modelo exacto | M1: 3. Foto o video propio disponible | Q1: 4. Precio vigente (₡) | U1: 5. Costo unitario (₡) · CONFIDENCIAL | Y1: 6. Stock (unidades) | AC1: 7. Compatibilidad comprobada (con qué y cómo) | AG1: 8. Características comprobadas (conexión, iluminación, botones…) | AK1: 9. Garantía: plazo | AO1: 10. Garantía: quién la da | AS1: 11. Entrega: zonas | AW1: 12. Entrega: costo (₡) | BA1: 13. Entrega: plazo | BE1: 14. Origen / autenticidad | BI1: 15. Contenido incluido y permisos de gameplay o música (RETRO) | BM1: 16. Quién aprueba los claims
E2: Valor | F2: Fuente / cómo se comprobó | G2: Fecha | H2: ¿Verificado? | I2: Valor | J2: Fuente / cómo se comprobó | K2: Fecha | L2: ¿Verificado? | M2: Valor | N2: Fuente / cómo se comprobó | O2: Fecha | P2: ¿Verificado? | Q2: Valor | R2: Fuente / cómo se comprobó | S2: Fecha | T2: ¿Verificado? | U2: Valor | V2: Fuente / cómo se comprobó | W2: Fecha | X2: ¿Verificado? | Y2: Valor | Z2: Fuente / cómo se comprobó | AA2: Fecha | AB2: ¿Verificado? | AC2: Valor | AD2: Fuente / cómo se comprobó | AE2: Fecha | AF2: ¿Verificado? | AG2: Valor | AH2: Fuente / cómo se comprobó | AI2: Fecha | AJ2: ¿Verificado? | AK2: Valor | AL2: Fuente / cómo se comprobó | AM2: Fecha | AN2: ¿Verificado? | AO2: Valor | AP2: Fuente / cómo se comprobó | AQ2: Fecha | AR2: ¿Verificado? | AS2: Valor | AT2: Fuente / cómo se comprobó | AU2: Fecha | AV2: ¿Verificado? | AW2: Valor | AX2: Fuente / cómo se comprobó | AY2: Fecha | AZ2: ¿Verificado? | BA2: Valor | BB2: Fuente / cómo se comprobó | BC2: Fecha | BD2: ¿Verificado? | BE2: Valor | BF2: Fuente / cómo se comprobó | BG2: Fecha | BH2: ¿Verificado? | BI2: Valor | BJ2: Fuente / cómo se comprobó | BK2: Fecha | BL2: ¿Verificado? | BM2: Valor | BN2: Fuente / cómo se comprobó | BO2: Fecha | BP2: ¿Verificado?
A3: GAME | B3: Audífonos gaming (mismo SKU para GAME1 y GAME2) | C3: =IF(D3=16,"COMPLETA","INCOMPLETA: faltan "&(16-D3)&" campos") -> INCOMPLETA: faltan 16 campos | D3: =SUMPRODUCT((MOD(COLUMN(E3:BP3)-COLUMN($E$3),4)=3)*((E3:BP3="Sí")+(E3:BP3="No aplica"))) -> 0
A4: RETRO | B4: Consola portátil retro (RETRO1) | C4: =IF(D4=16,"COMPLETA","INCOMPLETA: faltan "&(16-D4)&" campos") -> INCOMPLETA: faltan 16 campos | D4: =SUMPRODUCT((MOD(COLUMN(E4:BP4)-COLUMN($E$4),4)=3)*((E4:BP4="Sí")+(E4:BP4="No aplica"))) -> 0
A5: RGB | B5: Mouse o periférico gaming, o accesorio sustituto validado (RGB1) | C5: =IF(D5=16,"COMPLETA","INCOMPLETA: faltan "&(16-D5)&" campos") -> INCOMPLETA: faltan 16 campos | D5: =SUMPRODUCT((MOD(COLUMN(E5:BP5)-COLUMN($E$5),4)=3)*((E5:BP5="Sí")+(E5:BP5="No aplica"))) -> 0
A7: Regla: ningún claim entra a un guion hasta que su campo diga ¿Verificado? = Sí. GAME1 y GAME2 usan la misma fila GAME. El costo unitario es confidencial.

Sheet Consultas
A1: N.º de consulta | B1: Fecha | C1: Canal de origen (dónde nos vio) | D1: Código de pieza | E1: Producto consultado | F1: Zona | G1: ¿Consulta repetida? | H1: Cualificada | I1: Cotizada | J1: Pedido confirmado | K1: Cobrado | L1: Monto cobrado (₡) | M1: Minutos hasta la primera respuesta | N1: Objeción principal | O1: Nota breve (sin datos personales)
A2: =IF(AND(B2="",D2=""),"",ROW()-1)
A3: =IF(AND(B3="",D3=""),"",ROW()-1)
A4: =IF(AND(B4="",D4=""),"",ROW()-1)
A5: =IF(AND(B5="",D5=""),"",ROW()-1)
A6: =IF(AND(B6="",D6=""),"",ROW()-1)
A7: =IF(AND(B7="",D7=""),"",ROW()-1)
A8: =IF(AND(B8="",D8=""),"",ROW()-1)
A9: =IF(AND(B9="",D9=""),"",ROW()-1)
A10: =IF(AND(B10="",D10=""),"",ROW()-1)
A11: =IF(AND(B11="",D11=""),"",ROW()-1)
A12: =IF(AND(B12="",D12=""),"",ROW()-1)
A13: =IF(AND(B13="",D13=""),"",ROW()-1)
... A301: =IF(AND(B301="",D301=""),"",ROW()-1)

Sheet Resumen
A1: Resumen de la prueba · El Tilichero
A2: Cuenta solo consultas únicas (¿Consulta repetida? distinto de Sí) con fecha dentro del periodo. Amarillo = llenar a mano; gris = se calcula solo.
A4: Desde | C4: Vacía = desde el inicio del registro.
A5: Hasta | C5: Vacía = hasta el final del registro. La pauta de abajo debe ser la de ESTAS mismas fechas.
A6: Estado del registro | B6: =IF(SUM(I98:I105)=0,"Sin inconsistencias detectadas en «Consultas».","Hay "&SUM(I98:I105)&" inconsistencias: revisá las filas en rojo de «Consultas» y el control al final de esta hoja.") -> Sin inconsistencias detectadas en «Consultas».
A8: Embudo por código de pieza
A9: Código | B9: Consultas únicas | C9: Cualificadas | D9: Cotizaciones | E9: Pedidos confirmados | F9: Cobrados | G9: Ingresos cobrados (₡) | H9: Inversión en pauta (₡) · escribir a mano | I9: Cualificadas / consultas | J9: Pedidos / cualificadas | K9: Costo por consulta cualificada (₡) | L9: Cualificadas / alcance
A10: GAME1 | B10: =COUNTIFS(Consultas!$D$2:$D$1000,$A10,Consultas!$G$2:$G$1000,"<>Sí",Consultas!$B$2:$B$1000,">="&IF($B$4="",1,$B$4),Consultas!$B$2:$B$1000,"<="&IF($B$5="",2958465,$B$5)) -> 0 | C10: =COUNTIFS(Consultas!$D$2:$D$1000,$A10,Consultas!$G$2:$G$1000,"<>Sí",Consultas!$B$2:$B$1000,">="&IF($B$4="",1,$B$4),Consultas!$B$2:$B$1000,"<="&IF($B$5="",2958465,$B$5),Consultas!$H$2:$H$1000,"Sí") -> 0 | D10: =COUNTIFS(Consultas!$D$2:$D$1000,$A10,Consultas!$G$2:$G$1000,"<>Sí",Consultas!$B$2:$B$1000,">="&IF($B$4="",1,$B$4),Consultas!$B$2:$B$1000,"<="&IF($B$5="",2958465,$B$5),Consultas!$I$2:$I$1000,"Sí") -> 0 | E10: =COUNTIFS(Consultas!$D$2:$D$1000,$A10,Consultas!$G$2:$G$1000,"<>Sí",Consultas!$B$2:$B$1000,">="&IF($B$4="",1,$B$4),Consultas!$B$2:$B$1000,"<="&IF($B$5="",2958465,$B$5),Consultas!$J$2:$J$1000,"Sí") -> 0 | F10: =COUNTIFS(Consultas!$D$2:$D$1000,$A10,Consultas!$G$2:$G$1000,"<>Sí",Consultas!$B$2:$B$1000,">="&IF($B$4="",1,$B$4),Consultas!$B$2:$B$1000,"<="&IF($B$5="",2958465,$B$5),Consultas!$K$2:$K$1000,"Sí") -> 0 | G10: =SUMIFS(Consultas!$L$2:$L$1000,Consultas!$D$2:$D$1000,$A10,Consultas!$G$2:$G$1000,"<>Sí",Consultas!$B$2:$B$1000,">="&IF($B$4="",1,$B$4),Consultas!$B$2:$B$1000,"<="&IF($B$5="",2958465,$B$5),Consultas!$K$2:$K$1000,"Sí") -> 0 | I10: =IF(B10=0,"NO CALCULABLE",C10/B10) -> NO CALCULABLE | J10: =IF(C10=0,"NO CALCULABLE",E10/C10) -> NO CALCULABLE | K10: =IF(C10=0,"NO CALCULABLE",IF(N(H10)<=0,"SIN PAUTA",H10/C10)) -> NO CALCULABLE | L10: =IF(N($E$26)=0,"NO CALCULABLE",C10/$E$26) -> NO CALCULABLE
A11: GAME2 | B11: =COUNTIFS(Consultas!$D$2:$D$1000,$A11,Consultas!$G$2:$G$1000,"<>Sí",Consultas!$B$2:$B$1000,">="&IF($B$4="",1,$B$4),Consultas!$B$2:$B$1000,"<="&IF($B$5="",2958465,$B$5)) -> 0 | C11: =COUNTIFS(Consultas!$D$2:$D$1000,$A11,Consultas!$G$2:$G$1000,"<>Sí",Consultas!$B$2:$B$1000,">="&IF($B$4="",1,$B$4),Consultas!$B$2:$B$1000,"<="&IF($B$5="",2958465,$B$5),Consultas!$H$2:$H$1000,"Sí") -> 0 | D11: =COUNTIFS(Consultas!$D$2:$D$1000,$A11,Consultas!$G$2:$G$1000,"<>Sí",Consultas!$B$2:$B$1000,">="&IF($B$4="",1,$B$4),Consultas!$B$2:$B$1000,"<="&IF($B$5="",2958465,$B$5),Consultas!$I$2:$I$1000,"Sí") -> 0 | E11: =COUNTIFS(Consultas!$D$2:$D$1000,$A11,Consultas!$G$2:$G$1000,"<>Sí",Consultas!$B$2:$B$1000,">="&IF($B$4="",1,$B$4),Consultas!$B$2:$B$1000,"<="&IF($B$5="",2958465,$B$5),Consultas!$J$2:$J$1000,"Sí") -> 0 | F11: =COUNTIFS(Consultas!$D$2:$D$1000,$A11,Consultas!$G$2:$G$1000,"<>Sí",Consultas!$B$2:$B$1000,">="&IF($B$4="",1,$B$4),Consultas!$B$2:$B$1000,"<="&IF($B$5="",2958465,$B$5),Consultas!$K$2:$K$1000,"Sí") -> 0 | G11: =SUMIFS(Consultas!$L$2:$L$1000,Consultas!$D$2:$D$1000,$A11,Consultas!$G$2:$G$1000,"<>Sí",Consultas!$B$2:$B$1000,">="&IF($B$4="",1,$B$4),Consultas!$B$2:$B$1000,"<="&IF($B$5="",2958465,$B$5),Consultas!$K$2:$K$1000,"Sí") -> 0 | I11: =IF(B11=0,"NO CALCULABLE",C11/B11) -> NO CALCULABLE | J11: =IF(C11=0,"NO CALCULABLE",E11/C11) -> NO CALCULABLE | K11: =IF(C11=0,"NO CALCULABLE",IF(N(H11)<=0,"SIN PAUTA",H11/C11)) -> NO CALCULABLE | L11: =IF(N($E$27)=0,"NO CALCULABLE",C11/$E$27) -> NO CALCULABLE
A12: RETRO1 | B12: =COUNTIFS(Consultas!$D$2:$D$1000,$A12,Consultas!$G$2:$G$1000,"<>Sí",Consultas!$B$2:$B$1000,">="&IF($B$4="",1,$B$4),Consultas!$B$2:$B$1000,"<="&IF($B$5="",2958465,$B$5)) -> 0 | C12: =COUNTIFS(Consultas!$D$2:$D$1000,$A12,Consultas!$G$2:$G$1000,"<>Sí",Consultas!$B$2:$B$1000,">="&IF($B$4="",1,$B$4),Consultas!$B$2:$B$1000,"<="&IF($B$5="",2958465,$B$5),Consultas!$H$2:$H$1000,"Sí") -> 0 | D12: =COUNTIFS(Consultas!$D$2:$D$1000,$A12,Consultas!$G$2:$G$1000,"<>Sí",Consultas!$B$2:$B$1000,">="&IF($B$4="",1,$B$4),Consultas!$B$2:$B$1000,"<="&IF($B$5="",2958465,$B$5),Consultas!$I$2:$I$1000,"Sí") -> 0 | E12: =COUNTIFS(Consultas!$D$2:$D$1000,$A12,Consultas!$G$2:$G$1000,"<>Sí",Consultas!$B$2:$B$1000,">="&IF($B$4="",1,$B$4),Consultas!$B$2:$B$1000,"<="&IF($B$5="",2958465,$B$5),Consultas!$J$2:$J$1000,"Sí") -> 0 | F12: =COUNTIFS(Consultas!$D$2:$D$1000,$A12,Consultas!$G$2:$G$1000,"<>Sí",Consultas!$B$2:$B$1000,">="&IF($B$4="",1,$B$4),Consultas!$B$2:$B$1000,"<="&IF($B$5="",2958465,$B$5),Consultas!$K$2:$K$1000,"Sí") -> 0 | G12: =SUMIFS(Consultas!$L$2:$L$1000,Consultas!$D$2:$D$1000,$A12,Consultas!$G$2:$G$1000,"<>Sí",Consultas!$B$2:$B$1000,">="&IF($B$4="",1,$B$4),Consultas!$B$2:$B$1000,"<="&IF($B$5="",2958465,$B$5),Consultas!$K$2:$K$1000,"Sí") -> 0 | I12: =IF(B12=0,"NO CALCULABLE",C12/B12) -> NO CALCULABLE | J12: =IF(C12=0,"NO CALCULABLE",E12/C12) -> NO CALCULABLE | K12: =IF(C12=0,"NO CALCULABLE",IF(N(H12)<=0,"SIN PAUTA",H12/C12)) -> NO CALCULABLE | L12: =IF(N($E$28)=0,"NO CALCULABLE",C12/$E$28) -> NO CALCULABLE
A13: RGB1 | B13: =COUNTIFS(Consultas!$D$2:$D$1000,$A13,Consultas!$G$2:$G$1000,"<>Sí",Consultas!$B$2:$B$1000,">="&IF($B$4="",1,$B$4),Consultas!$B$2:$B$1000,"<="&IF($B$5="",2958465,$B$5)) -> 0 | C13: =COUNTIFS(Consultas!$D$2:$D$1000,$A13,Consultas!$G$2:$G$1000,"<>Sí",Consultas!$B$2:$B$1000,">="&IF($B$4="",1,$B$4),Consultas!$B$2:$B$1000,"<="&IF($B$5="",2958465,$B$5),Consultas!$H$2:$H$1000,"Sí") -> 0 | D13: =COUNTIFS(Consultas!$D$2:$D$1000,$A13,Consultas!$G$2:$G$1000,"<>Sí",Consultas!$B$2:$B$1000,">="&IF($B$4="",1,$B$4),Consultas!$B$2:$B$1000,"<="&IF($B$5="",2958465,$B$5),Consultas!$I$2:$I$1000,"Sí") -> 0 | E13: =COUNTIFS(Consultas!$D$2:$D$1000,$A13,Consultas!$G$2:$G$1000,"<>Sí",Consultas!$B$2:$B$1000,">="&IF($B$4="",1,$B$4),Consultas!$B$2:$B$1000,"<="&IF($B$5="",2958465,$B$5),Consultas!$J$2:$J$1000,"Sí") -> 0 | F13: =COUNTIFS(Consultas!$D$2:$D$1000,$A13,Consultas!$G$2:$G$1000,"<>Sí",Consultas!$B$2:$B$1000,">="&IF($B$4="",1,$B$4),Consultas!$B$2:$B$1000,"<="&IF($B$5="",2958465,$B$5),Consultas!$K$2:$K$1000,"Sí") -> 0 | G13: =SUMIFS(Consultas!$L$2:$L$1000,Consultas!$D$2:$D$1000,$A13,Consultas!$G$2:$G$1000,"<>Sí",Consultas!$B$2:$B$1000,">="&IF($B$4="",1,$B$4),Consultas!$B$2:$B$1000,"<="&IF($B$5="",2958465,$B$5),Consultas!$K$2:$K$1000,"Sí") -> 0 | I13: =IF(B13=0,"NO CALCULABLE",C13/B13) -> NO CALCULABLE | J13: =IF(C13=0,"NO CALCULABLE",E13/C13) -> NO CALCULABLE | K13: =IF(C13=0,"NO CALCULABLE",IF(N(H13)<=0,"SIN PAUTA",H13/C13)) -> NO CALCULABLE | L13: =IF(N($E$29)=0,"NO CALCULABLE",C13/$E$29) -> NO CALCULABLE
A14: OTRO | B14: =COUNTIFS(Consultas!$D$2:$D$1000,$A14,Consultas!$G$2:$G$1000,"<>Sí",Consultas!$B$2:$B$1000,">="&IF($B$4="",1,$B$4),Consultas!$B$2:$B$1000,"<="&IF($B$5="",2958465,$B$5)) -> 0 | C14: =COUNTIFS(Consultas!$D$2:$D$1000,$A14,Consultas!$G$2:$G$1000,"<>Sí",Consultas!$B$2:$B$1000,">="&IF($B$4="",1,$B$4),Consultas!$B$2:$B$1000,"<="&IF($B$5="",2958465,$B$5),Consultas!$H$2:$H$1000,"Sí") -> 0 | D14: =COUNTIFS(Consultas!$D$2:$D$1000,$A14,Consultas!$G$2:$G$1000,"<>Sí",Consultas!$B$2:$B$1000,">="&IF($B$4="",1,$B$4),Consultas!$B$2:$B$1000,"<="&IF($B$5="",2958465,$B$5),Consultas!$I$2:$I$1000,"Sí") -> 0 | E14: =COUNTIFS(Consultas!$D$2:$D$1000,$A14,Consultas!$G$2:$G$1000,"<>Sí",Consultas!$B$2:$B$1000,">="&IF($B$4="",1,$B$4),Consultas!$B$2:$B$1000,"<="&IF($B$5="",2958465,$B$5),Consultas!$J$2:$J$1000,"Sí") -> 0 | F14: =COUNTIFS(Consultas!$D$2:$D$1000,$A14,Consultas!$G$2:$G$1000,"<>Sí",Consultas!$B$2:$B$1000,">="&IF($B$4="",1,$B$4),Consultas!$B$2:$B$1000,"<="&IF($B$5="",2958465,$B$5),Consultas!$K$2:$K$1000,"Sí") -> 0 | G14: =SUMIFS(Consultas!$L$2:$L$1000,Consultas!$D$2:$D$1000,$A14,Consultas!$G$2:$G$1000,"<>Sí",Consultas!$B$2:$B$1000,">="&IF($B$4="",1,$B$4),Consultas!$B$2:$B$1000,"<="&IF($B$5="",2958465,$B$5),Consultas!$K$2:$K$1000,"Sí") -> 0 | H14: No aplica | I14: =IF(B14=0,"NO CALCULABLE",C14/B14) -> NO CALCULABLE | J14: =IF(C14=0,"NO CALCULABLE",E14/C14) -> NO CALCULABLE | K14: =IF(C14=0,"NO CALCULABLE",IF(N(H14)<=0,"SIN PAUTA",H14/C14)) -> NO CALCULABLE | L14: No aplica
A15: SIN CODIGO | B15: =COUNTIFS(Consultas!$D$2:$D$1000,$A15,Consultas!$G$2:$G$1000,"<>Sí",Consultas!$B$2:$B$1000,">="&IF($B$4="",1,$B$4),Consultas!$B$2:$B$1000,"<="&IF($B$5="",2958465,$B$5)) -> 0 | C15: =COUNTIFS(Consultas!$D$2:$D$1000,$A15,Consultas!$G$2:$G$1000,"<>Sí",Consultas!$B$2:$B$1000,">="&IF($B$4="",1,$B$4),Consultas!$B$2:$B$1000,"<="&IF($B$5="",2958465,$B$5),Consultas!$H$2:$H$1000,"Sí") -> 0 | D15: =COUNTIFS(Consultas!$D$2:$D$1000,$A15,Consultas!$G$2:$G$1000,"<>Sí",Consultas!$B$2:$B$1000,">="&IF($B$4="",1,$B$4),Consultas!$B$2:$B$1000,"<="&IF($B$5="",2958465,$B$5),Consultas!$I$2:$I$1000,"Sí") -> 0 | E15: =COUNTIFS(Consultas!$D$2:$D$1000,$A15,Consultas!$G$2:$G$1000,"<>Sí",Consultas!$B$2:$B$1000,">="&IF($B$4="",1,$B$4),Consultas!$B$2:$B$1000,"<="&IF($B$5="",2958465,$B$5),Consultas!$J$2:$J$1000,"Sí") -> 0 | F15: =COUNTIFS(Consultas!$D$2:$D$1000,$A15,Consultas!$G$2:$G$1000,"<>Sí",Consultas!$B$2:$B$1000,">="&IF($B$4="",1,$B$4),Consultas!$B$2:$B$1000,"<="&IF($B$5="",2958465,$B$5),Consultas!$K$2:$K$1000,"Sí") -> 0 | G15: =SUMIFS(Consultas!$L$2:$L$1000,Consultas!$D$2:$D$1000,$A15,Consultas!$G$2:$G$1000,"<>Sí",Consultas!$B$2:$B$1000,">="&IF($B$4="",1,$B$4),Consultas!$B$2:$B$1000,"<="&IF($B$5="",2958465,$B$5),Consultas!$K$2:$K$1000,"Sí") -> 0 | H15: No aplica | I15: =IF(B15=0,"NO CALCULABLE",C15/B15) -> NO CALCULABLE | J15: =IF(C15=0,"NO CALCULABLE",E15/C15) -> NO CALCULABLE | K15: =IF(C15=0,"NO CALCULABLE",IF(N(H15)<=0,"SIN PAUTA",H15/C15)) -> NO CALCULABLE | L15: No aplica
A16: Total | B16: =SUM(B10:B15) -> 0 | C16: =SUM(C10:C15) -> 0 | D16: =SUM(D10:D15) -> 0 | E16: =SUM(E10:E15) -> 0 | F16: =SUM(F10:F15) -> 0 | G16: =SUM(G10:G15) -> 0 | H16: =IF(SUMIF($H$10:$H$13,">0")=0,"SIN PAUTA",SUMIF($H$10:$H$13,">0")) -> SIN PAUTA | I16: =IF(B16=0,"NO CALCULABLE",C16/B16) -> NO CALCULABLE | J16: =IF(C16=0,"NO CALCULABLE",E16/C16) -> NO CALCULABLE | K16: =IF(C16=0,"NO CALCULABLE",IF(SUMIF($H$10:$H$13,">0")=0,"SIN PAUTA",IF(SUMIF($H$10:$H$13,">0",$C$10:$C$13)=0,"NO CALCULABLE",SUMIF($H$10:$H$13,">0")/SUMIF($H$10:$H$13,">0",$C$10:$C$13)))) -> NO CALCULABLE | L16: =IF(SUMIF($E$26:$E$29,">0")=0,"NO CALCULABLE",SUMIF($E$26:$E$29,">0",$C$10:$C$13)/SUMIF($E$26:$E$29,">0")) -> NO CALCULABLE
A17: NO CALCULABLE = el denominador es 0 o está vacío; no significa 0 %. SIN PAUTA = no hay inversión escrita.
A18: Ingresos cobrados no es venta neta: faltan devoluciones, descuentos, costo del producto y envío.
A19: Las piezas salen en días distintos: este cuadro suma, no compara piezas. GAME1 frente a GAME2 se mira en el bloque «Prueba A».
A20: Cualificadas / alcance usa el bloque de alcance de abajo (mismo periodo Desde/Hasta). Sin alcance: NO CALCULABLE, y se miran los volúmenes absolutos.
A22: Alcance por pieza y plataforma (de Insights, escribir a mano)
A23: Tiene que ser del MISMO periodo que Desde/Hasta: leé el alcance el día «Hasta». Anotá cuentas o personas alcanzadas, no reproducciones.
A24: Solo números totales, sin datos de personas. Dejá vacía la plataforma donde la pieza no se publicó. La suma puede contar dos veces a quien vio la pieza en dos plataformas.
A25: Pieza | B25: Instagram | C25: Facebook | D25: TikTok | E25: Total | F25: Leído el (fecha)
A26: GAME1 | E26: =IF(COUNT(B26:D26)=0,"SIN DATO",SUM(B26:D26)) -> SIN DATO
A27: GAME2 | E27: =IF(COUNT(B27:D27)=0,"SIN DATO",SUM(B27:D27)) -> SIN DATO
A28: RETRO1 | E28: =IF(COUNT(B28:D28)=0,"SIN DATO",SUM(B28:D28)) -> SIN DATO
A29: RGB1 | E29: =IF(COUNT(B29:D29)=0,"SIN DATO",SUM(B29:D29)) -> SIN DATO
A31: Embudo por canal de origen
A32: Mismo filtro Desde/Hasta y misma regla de repetidas que el embudo por código. Cuenta las consultas con código de pieza (OTRO y SIN CODIGO incluidos).
A33: La pauta de este cuadro y la del embudo por código NO se suman: es el mismo gasto visto de dos formas. Anotala en un solo lugar:
A34: si el anuncio usa una pieza con código (GAME1, GAME2, RETRO1, RGB1), en el embudo por código; si no tiene código (por ejemplo, un anuncio con foto), aquí en «Anuncio pagado (Meta)».
A35: Canal de origen | B35: Consultas únicas | C35: Cualificadas | D35: Cotizaciones | E35: Pedidos confirmados | F35: Cobrados | G35: Ingresos cobrados (₡) | H35: Inversión en pauta (₡) · escribir a mano | I35: Cualificadas / consultas | J35: Pedidos / cualificadas | K35: Costo por consulta cualificada (₡)
A36: Instagram | B36: =COUNTIFS(Consultas!$C$2:$C$1000,$A36,Consultas!$D$2:$D$1000,"<>",Consultas!$G$2:$G$1000,"<>Sí",Consultas!$B$2:$B$1000,">="&IF($B$4="",1,$B$4),Consultas!$B$2:$B$1000,"<="&IF($B$5="",2958465,$B$5)) -> 0 | C36: =COUNTIFS(Consultas!$C$2:$C$1000,$A36,Consultas!$D$2:$D$1000,"<>",Consultas!$G$2:$G$1000,"<>Sí",Consultas!$B$2:$B$1000,">="&IF($B$4="",1,$B$4),Consultas!$B$2:$B$1000,"<="&IF($B$5="",2958465,$B$5),Consultas!$H$2:$H$1000,"Sí") -> 0 | D36: =COUNTIFS(Consultas!$C$2:$C$1000,$A36,Consultas!$D$2:$D$1000,"<>",Consultas!$G$2:$G$1000,"<>Sí",Consultas!$B$2:$B$1000,">="&IF($B$4="",1,$B$4),Consultas!$B$2:$B$1000,"<="&IF($B$5="",2958465,$B$5),Consultas!$I$2:$I$1000,"Sí") -> 0 | E36: =COUNTIFS(Consultas!$C$2:$C$1000,$A36,Consultas!$D$2:$D$1000,"<>",Consultas!$G$2:$G$1000,"<>Sí",Consultas!$B$2:$B$1000,">="&IF($B$4="",1,$B$4),Consultas!$B$2:$B$1000,"<="&IF($B$5="",2958465,$B$5),Consultas!$J$2:$J$1000,"Sí") -> 0 | F36: =COUNTIFS(Consultas!$C$2:$C$1000,$A36,Consultas!$D$2:$D$1000,"<>",Consultas!$G$2:$G$1000,"<>Sí",Consultas!$B$2:$B$1000,">="&IF($B$4="",1,$B$4),Consultas!$B$2:$B$1000,"<="&IF($B$5="",2958465,$B$5),Consultas!$K$2:$K$1000,"Sí") -> 0 | G36: =SUMIFS(Consultas!$L$2:$L$1000,Consultas!$C$2:$C$1000,$A36,Consultas!$D$2:$D$1000,"<>",Consultas!$G$2:$G$1000,"<>Sí",Consultas!$B$2:$B$1000,">="&IF($B$4="",1,$B$4),Consultas!$B$2:$B$1000,"<="&IF($B$5="",2958465,$B$5),Consultas!$K$2:$K$1000,"Sí") -> 0 | H36: No aplica | I36: =IF(B36=0,"NO CALCULABLE",C36/B36) -> NO CALCULABLE | J36: =IF(C36=0,"NO CALCULABLE",E36/C36) -> NO CALCULABLE | K36: No aplica
A37: Facebook (página) | B37: =COUNTIFS(Consultas!$C$2:$C$1000,$A37,Consultas!$D$2:$D$1000,"<>",Consultas!$G$2:$G$1000,"<>Sí",Consultas!$B$2:$B$1000,">="&IF($B$4="",1,$B$4),Consultas!$B$2:$B$1000,"<="&IF($B$5="",2958465,$B$5)) -> 0 | C37: =COUNTIFS(Consultas!$C$2:$C$1000,$A37,Consultas!$D$2:$D$1000,"<>",Consultas!$G$2:$G$1000,"<>Sí",Consultas!$B$2:$B$1000,">="&IF($B$4="",1,$B$4),Consultas!$B$2:$B$1000,"<="&IF($B$5="",2958465,$B$5),Consultas!$H$2:$H$1000,"Sí") -> 0 | D37: =COUNTIFS(Consultas!$C$2:$C$1000,$A37,Consultas!$D$2:$D$1000,"<>",Consultas!$G$2:$G$1000,"<>Sí",Consultas!$B$2:$B$1000,">="&IF($B$4="",1,$B$4),Consultas!$B$2:$B$1000,"<="&IF($B$5="",2958465,$B$5),Consultas!$I$2:$I$1000,"Sí") -> 0 | E37: =COUNTIFS(Consultas!$C$2:$C$1000,$A37,Consultas!$D$2:$D$1000,"<>",Consultas!$G$2:$G$1000,"<>Sí",Consultas!$B$2:$B$1000,">="&IF($B$4="",1,$B$4),Consultas!$B$2:$B$1000,"<="&IF($B$5="",2958465,$B$5),Consultas!$J$2:$J$1000,"Sí") -> 0 | F37: =COUNTIFS(Consultas!$C$2:$C$1000,$A37,Consultas!$D$2:$D$1000,"<>",Consultas!$G$2:$G$1000,"<>Sí",Consultas!$B$2:$B$1000,">="&IF($B$4="",1,$B$4),Consultas!$B$2:$B$1000,"<="&IF($B$5="",2958465,$B$5),Consultas!$K$2:$K$1000,"Sí") -> 0 | G37: =SUMIFS(Consultas!$L$2:$L$1000,Consultas!$C$2:$C$1000,$A37,Consultas!$D$2:$D$1000,"<>",Consultas!$G$2:$G$1000,"<>Sí",Consultas!$B$2:$B$1000,">="&IF($B$4="",1,$B$4),Consultas!$B$2:$B$1000,"<="&IF($B$5="",2958465,$B$5),Consultas!$K$2:$K$1000,"Sí") -> 0 | H37: No aplica | I37: =IF(B37=0,"NO CALCULABLE",C37/B37) -> NO CALCULABLE | J37: =IF(C37=0,"NO CALCULABLE",E37/C37) -> NO CALCULABLE | K37: No aplica
A38: Facebook Marketplace | B38: =COUNTIFS(Consultas!$C$2:$C$1000,$A38,Consultas!$D$2:$D$1000,"<>",Consultas!$G$2:$G$1000,"<>Sí",Consultas!$B$2:$B$1000,">="&IF($B$4="",1,$B$4),Consultas!$B$2:$B$1000,"<="&IF($B$5="",2958465,$B$5)) -> 0 | C38: =COUNTIFS(Consultas!$C$2:$C$1000,$A38,Consultas!$D$2:$D$1000,"<>",Consultas!$G$2:$G$1000,"<>Sí",Consultas!$B$2:$B$1000,">="&IF($B$4="",1,$B$4),Consultas!$B$2:$B$1000,"<="&IF($B$5="",2958465,$B$5),Consultas!$H$2:$H$1000,"Sí") -> 0 | D38: =COUNTIFS(Consultas!$C$2:$C$1000,$A38,Consultas!$D$2:$D$1000,"<>",Consultas!$G$2:$G$1000,"<>Sí",Consultas!$B$2:$B$1000,">="&IF($B$4="",1,$B$4),Consultas!$B$2:$B$1000,"<="&IF($B$5="",2958465,$B$5),Consultas!$I$2:$I$1000,"Sí") -> 0 | E38: =COUNTIFS(Consultas!$C$2:$C$1000,$A38,Consultas!$D$2:$D$1000,"<>",Consultas!$G$2:$G$1000,"<>Sí",Consultas!$B$2:$B$1000,">="&IF($B$4="",1,$B$4),Consultas!$B$2:$B$1000,"<="&IF($B$5="",2958465,$B$5),Consultas!$J$2:$J$1000,"Sí") -> 0 | F38: =COUNTIFS(Consultas!$C$2:$C$1000,$A38,Consultas!$D$2:$D$1000,"<>",Consultas!$G$2:$G$1000,"<>Sí",Consultas!$B$2:$B$1000,">="&IF($B$4="",1,$B$4),Consultas!$B$2:$B$1000,"<="&IF($B$5="",2958465,$B$5),Consultas!$K$2:$K$1000,"Sí") -> 0 | G38: =SUMIFS(Consultas!$L$2:$L$1000,Consultas!$C$2:$C$1000,$A38,Consultas!$D$2:$D$1000,"<>",Consultas!$G$2:$G$1000,"<>Sí",Consultas!$B$2:$B$1000,">="&IF($B$4="",1,$B$4),Consultas!$B$2:$B$1000,"<="&IF($B$5="",2958465,$B$5),Consultas!$K$2:$K$1000,"Sí") -> 0 | H38: No aplica | I38: =IF(B38=0,"NO CALCULABLE",C38/B38) -> NO CALCULABLE | J38: =IF(C38=0,"NO CALCULABLE",E38/C38) -> NO CALCULABLE | K38: No aplica
A39: Grupo de Facebook | B39: =COUNTIFS(Consultas!$C$2:$C$1000,$A39,Consultas!$D$2:$D$1000,"<>",Consultas!$G$2:$G$1000,"<>Sí",Consultas!$B$2:$B$1000,">="&IF($B$4="",1,$B$4),Consultas!$B$2:$B$1000,"<="&IF($B$5="",2958465,$B$5)) -> 0 | C39: =COUNTIFS(Consultas!$C$2:$C$1000,$A39,Consultas!$D$2:$D$1000,"<>",Consultas!$G$2:$G$1000,"<>Sí",Consultas!$B$2:$B$1000,">="&IF($B$4="",1,$B$4),Consultas!$B$2:$B$1000,"<="&IF($B$5="",2958465,$B$5),Consultas!$H$2:$H$1000,"Sí") -> 0 | D39: =COUNTIFS(Consultas!$C$2:$C$1000,$A39,Consultas!$D$2:$D$1000,"<>",Consultas!$G$2:$G$1000,"<>Sí",Consultas!$B$2:$B$1000,">="&IF($B$4="",1,$B$4),Consultas!$B$2:$B$1000,"<="&IF($B$5="",2958465,$B$5),Consultas!$I$2:$I$1000,"Sí") -> 0 | E39: =COUNTIFS(Consultas!$C$2:$C$1000,$A39,Consultas!$D$2:$D$1000,"<>",Consultas!$G$2:$G$1000,"<>Sí",Consultas!$B$2:$B$1000,">="&IF($B$4="",1,$B$4),Consultas!$B$2:$B$1000,"<="&IF($B$5="",2958465,$B$5),Consultas!$J$2:$J$1000,"Sí") -> 0 | F39: =COUNTIFS(Consultas!$C$2:$C$1000,$A39,Consultas!$D$2:$D$1000,"<>",Consultas!$G$2:$G$1000,"<>Sí",Consultas!$B$2:$B$1000,">="&IF($B$4="",1,$B$4),Consultas!$B$2:$B$1000,"<="&IF($B$5="",2958465,$B$5),Consultas!$K$2:$K$1000,"Sí") -> 0 | G39: =SUMIFS(Consultas!$L$2:$L$1000,Consultas!$C$2:$C$1000,$A39,Consultas!$D$2:$D$1000,"<>",Consultas!$G$2:$G$1000,"<>Sí",Consultas!$B$2:$B$1000,">="&IF($B$4="",1,$B$4),Consultas!$B$2:$B$1000,"<="&IF($B$5="",2958465,$B$5),Consultas!$K$2:$K$1000,"Sí") -> 0 | H39: No aplica | I39: =IF(B39=0,"NO CALCULABLE",C39/B39) -> NO CALCULABLE | J39: =IF(C39=0,"NO CALCULABLE",E39/C39) -> NO CALCULABLE | K39: No aplica
A40: TikTok | B40: =COUNTIFS(Consultas!$C$2:$C$1000,$A40,Consultas!$D$2:$D$1000,"<>",Consultas!$G$2:$G$1000,"<>Sí",Consultas!$B$2:$B$1000,">="&IF($B$4="",1,$B$4),Consultas!$B$2:$B$1000,"<="&IF($B$5="",2958465,$B$5)) -> 0 | C40: =COUNTIFS(Consultas!$C$2:$C$1000,$A40,Consultas!$D$2:$D$1000,"<>",Consultas!$G$2:$G$1000,"<>Sí",Consultas!$B$2:$B$1000,">="&IF($B$4="",1,$B$4),Consultas!$B$2:$B$1000,"<="&IF($B$5="",2958465,$B$5),Consultas!$H$2:$H$1000,"Sí") -> 0 | D40: =COUNTIFS(Consultas!$C$2:$C$1000,$A40,Consultas!$D$2:$D$1000,"<>",Consultas!$G$2:$G$1000,"<>Sí",Consultas!$B$2:$B$1000,">="&IF($B$4="",1,$B$4),Consultas!$B$2:$B$1000,"<="&IF($B$5="",2958465,$B$5),Consultas!$I$2:$I$1000,"Sí") -> 0 | E40: =COUNTIFS(Consultas!$C$2:$C$1000,$A40,Consultas!$D$2:$D$1000,"<>",Consultas!$G$2:$G$1000,"<>Sí",Consultas!$B$2:$B$1000,">="&IF($B$4="",1,$B$4),Consultas!$B$2:$B$1000,"<="&IF($B$5="",2958465,$B$5),Consultas!$J$2:$J$1000,"Sí") -> 0 | F40: =COUNTIFS(Consultas!$C$2:$C$1000,$A40,Consultas!$D$2:$D$1000,"<>",Consultas!$G$2:$G$1000,"<>Sí",Consultas!$B$2:$B$1000,">="&IF($B$4="",1,$B$4),Consultas!$B$2:$B$1000,"<="&IF($B$5="",2958465,$B$5),Consultas!$K$2:$K$1000,"Sí") -> 0 | G40: =SUMIFS(Consultas!$L$2:$L$1000,Consultas!$C$2:$C$1000,$A40,Consultas!$D$2:$D$1000,"<>",Consultas!$G$2:$G$1000,"<>Sí",Consultas!$B$2:$B$1000,">="&IF($B$4="",1,$B$4),Consultas!$B$2:$B$1000,"<="&IF($B$5="",2958465,$B$5),Consultas!$K$2:$K$1000,"Sí") -> 0 | H40: No aplica | I40: =IF(B40=0,"NO CALCULABLE",C40/B40) -> NO CALCULABLE | J40: =IF(C40=0,"NO CALCULABLE",E40/C40) -> NO CALCULABLE | K40: No aplica
A41: Estado de WhatsApp | B41: =COUNTIFS(Consultas!$C$2:$C$1000,$A41,Consultas!$D$2:$D$1000,"<>",Consultas!$G$2:$G$1000,"<>Sí",Consultas!$B$2:$B$1000,">="&IF($B$4="",1,$B$4),Consultas!$B$2:$B$1000,"<="&IF($B$5="",2958465,$B$5)) -> 0 | C41: =COUNTIFS(Consultas!$C$2:$C$1000,$A41,Consultas!$D$2:$D$1000,"<>",Consultas!$G$2:$G$1000,"<>Sí",Consultas!$B$2:$B$1000,">="&IF($B$4="",1,$B$4),Consultas!$B$2:$B$1000,"<="&IF($B$5="",2958465,$B$5),Consultas!$H$2:$H$1000,"Sí") -> 0 | D41: =COUNTIFS(Consultas!$C$2:$C$1000,$A41,Consultas!$D$2:$D$1000,"<>",Consultas!$G$2:$G$1000,"<>Sí",Consultas!$B$2:$B$1000,">="&IF($B$4="",1,$B$4),Consultas!$B$2:$B$1000,"<="&IF($B$5="",2958465,$B$5),Consultas!$I$2:$I$1000,"Sí") -> 0 | E41: =COUNTIFS(Consultas!$C$2:$C$1000,$A41,Consultas!$D$2:$D$1000,"<>",Consultas!$G$2:$G$1000,"<>Sí",Consultas!$B$2:$B$1000,">="&IF($B$4="",1,$B$4),Consultas!$B$2:$B$1000,"<="&IF($B$5="",2958465,$B$5),Consultas!$J$2:$J$1000,"Sí") -> 0 | F41: =COUNTIFS(Consultas!$C$2:$C$1000,$A41,Consultas!$D$2:$D$1000,"<>",Consultas!$G$2:$G$1000,"<>Sí",Consultas!$B$2:$B$1000,">="&IF($B$4="",1,$B$4),Consultas!$B$2:$B$1000,"<="&IF($B$5="",2958465,$B$5),Consultas!$K$2:$K$1000,"Sí") -> 0 | G41: =SUMIFS(Consultas!$L$2:$L$1000,Consultas!$C$2:$C$1000,$A41,Consultas!$D$2:$D$1000,"<>",Consultas!$G$2:$G$1000,"<>Sí",Consultas!$B$2:$B$1000,">="&IF($B$4="",1,$B$4),Consultas!$B$2:$B$1000,"<="&IF($B$5="",2958465,$B$5),Consultas!$K$2:$K$1000,"Sí") -> 0 | H41: No aplica | I41: =IF(B41=0,"NO CALCULABLE",C41/B41) -> NO CALCULABLE | J41: =IF(C41=0,"NO CALCULABLE",E41/C41) -> NO CALCULABLE | K41: No aplica
A42: Anuncio pagado (Meta) | B42: =COUNTIFS(Consultas!$C$2:$C$1000,$A42,Consultas!$D$2:$D$1000,"<>",Consultas!$G$2:$G$1000,"<>Sí",Consultas!$B$2:$B$1000,">="&IF($B$4="",1,$B$4),Consultas!$B$2:$B$1000,"<="&IF($B$5="",2958465,$B$5)) -> 0 | C42: =COUNTIFS(Consultas!$C$2:$C$1000,$A42,Consultas!$D$2:$D$1000,"<>",Consultas!$G$2:$G$1000,"<>Sí",Consultas!$B$2:$B$1000,">="&IF($B$4="",1,$B$4),Consultas!$B$2:$B$1000,"<="&IF($B$5="",2958465,$B$5),Consultas!$H$2:$H$1000,"Sí") -> 0 | D42: =COUNTIFS(Consultas!$C$2:$C$1000,$A42,Consultas!$D$2:$D$1000,"<>",Consultas!$G$2:$G$1000,"<>Sí",Consultas!$B$2:$B$1000,">="&IF($B$4="",1,$B$4),Consultas!$B$2:$B$1000,"<="&IF($B$5="",2958465,$B$5),Consultas!$I$2:$I$1000,"Sí") -> 0 | E42: =COUNTIFS(Consultas!$C$2:$C$1000,$A42,Consultas!$D$2:$D$1000,"<>",Consultas!$G$2:$G$1000,"<>Sí",Consultas!$B$2:$B$1000,">="&IF($B$4="",1,$B$4),Consultas!$B$2:$B$1000,"<="&IF($B$5="",2958465,$B$5),Consultas!$J$2:$J$1000,"Sí") -> 0 | F42: =COUNTIFS(Consultas!$C$2:$C$1000,$A42,Consultas!$D$2:$D$1000,"<>",Consultas!$G$2:$G$1000,"<>Sí",Consultas!$B$2:$B$1000,">="&IF($B$4="",1,$B$4),Consultas!$B$2:$B$1000,"<="&IF($B$5="",2958465,$B$5),Consultas!$K$2:$K$1000,"Sí") -> 0 | G42: =SUMIFS(Consultas!$L$2:$L$1000,Consultas!$C$2:$C$1000,$A42,Consultas!$D$2:$D$1000,"<>",Consultas!$G$2:$G$1000,"<>Sí",Consultas!$B$2:$B$1000,">="&IF($B$4="",1,$B$4),Consultas!$B$2:$B$1000,"<="&IF($B$5="",2958465,$B$5),Consultas!$K$2:$K$1000,"Sí") -> 0 | I42: =IF(B42=0,"NO CALCULABLE",C42/B42) -> NO CALCULABLE | J42: =IF(C42=0,"NO CALCULABLE",E42/C42) -> NO CALCULABLE | K42: =IF(C42=0,"NO CALCULABLE",IF(N(H42)<=0,"SIN PAUTA",H42/C42)) -> NO CALCULABLE
A43: Recomendación | B43: =COUNTIFS(Consultas!$C$2:$C$1000,$A43,Consultas!$D$2:$D$1000,"<>",Consultas!$G$2:$G$1000,"<>Sí",Consultas!$B$2:$B$1000,">="&IF($B$4="",1,$B$4),Consultas!$B$2:$B$1000,"<="&IF($B$5="",2958465,$B$5)) -> 0 | C43: =COUNTIFS(Consultas!$C$2:$C$1000,$A43,Consultas!$D$2:$D$1000,"<>",Consultas!$G$2:$G$1000,"<>Sí",Consultas!$B$2:$B$1000,">="&IF($B$4="",1,$B$4),Consultas!$B$2:$B$1000,"<="&IF($B$5="",2958465,$B$5),Consultas!$H$2:$H$1000,"Sí") -> 0 | D43: =COUNTIFS(Consultas!$C$2:$C$1000,$A43,Consultas!$D$2:$D$1000,"<>",Consultas!$G$2:$G$1000,"<>Sí",Consultas!$B$2:$B$1000,">="&IF($B$4="",1,$B$4),Consultas!$B$2:$B$1000,"<="&IF($B$5="",2958465,$B$5),Consultas!$I$2:$I$1000,"Sí") -> 0 | E43: =COUNTIFS(Consultas!$C$2:$C$1000,$A43,Consultas!$D$2:$D$1000,"<>",Consultas!$G$2:$G$1000,"<>Sí",Consultas!$B$2:$B$1000,">="&IF($B$4="",1,$B$4),Consultas!$B$2:$B$1000,"<="&IF($B$5="",2958465,$B$5),Consultas!$J$2:$J$1000,"Sí") -> 0 | F43: =COUNTIFS(Consultas!$C$2:$C$1000,$A43,Consultas!$D$2:$D$1000,"<>",Consultas!$G$2:$G$1000,"<>Sí",Consultas!$B$2:$B$1000,">="&IF($B$4="",1,$B$4),Consultas!$B$2:$B$1000,"<="&IF($B$5="",2958465,$B$5),Consultas!$K$2:$K$1000,"Sí") -> 0 | G43: =SUMIFS(Consultas!$L$2:$L$1000,Consultas!$C$2:$C$1000,$A43,Consultas!$D$2:$D$1000,"<>",Consultas!$G$2:$G$1000,"<>Sí",Consultas!$B$2:$B$1000,">="&IF($B$4="",1,$B$4),Consultas!$B$2:$B$1000,"<="&IF($B$5="",2958465,$B$5),Consultas!$K$2:$K$1000,"Sí") -> 0 | H43: No aplica | I43: =IF(B43=0,"NO CALCULABLE",C43/B43) -> NO CALCULABLE | J43: =IF(C43=0,"NO CALCULABLE",E43/C43) -> NO CALCULABLE | K43: No aplica
A44: Otro | B44: =COUNTIFS(Consultas!$C$2:$C$1000,$A44,Consultas!$D$2:$D$1000,"<>",Consultas!$G$2:$G$1000,"<>Sí",Consultas!$B$2:$B$1000,">="&IF($B$4="",1,$B$4),Consultas!$B$2:$B$1000,"<="&IF($B$5="",2958465,$B$5)) -> 0 | C44: =COUNTIFS(Consultas!$C$2:$C$1000,$A44,Consultas!$D$2:$D$1000,"<>",Consultas!$G$2:$G$1000,"<>Sí",Consultas!$B$2:$B$1000,">="&IF($B$4="",1,$B$4),Consultas!$B$2:$B$1000,"<="&IF($B$5="",2958465,$B$5),Consultas!$H$2:$H$1000,"Sí") -> 0 | D44: =COUNTIFS(Consultas!$C$2:$C$1000,$A44,Consultas!$D$2:$D$1000,"<>",Consultas!$G$2:$G$1000,"<>Sí",Consultas!$B$2:$B$1000,">="&IF($B$4="",1,$B$4),Consultas!$B$2:$B$1000,"<="&IF($B$5="",2958465,$B$5),Consultas!$I$2:$I$1000,"Sí") -> 0 | E44: =COUNTIFS(Consultas!$C$2:$C$1000,$A44,Consultas!$D$2:$D$1000,"<>",Consultas!$G$2:$G$1000,"<>Sí",Consultas!$B$2:$B$1000,">="&IF($B$4="",1,$B$4),Consultas!$B$2:$B$1000,"<="&IF($B$5="",2958465,$B$5),Consultas!$J$2:$J$1000,"Sí") -> 0 | F44: =COUNTIFS(Consultas!$C$2:$C$1000,$A44,Consultas!$D$2:$D$1000,"<>",Consultas!$G$2:$G$1000,"<>Sí",Consultas!$B$2:$B$1000,">="&IF($B$4="",1,$B$4),Consultas!$B$2:$B$1000,"<="&IF($B$5="",2958465,$B$5),Consultas!$K$2:$K$1000,"Sí") -> 0 | G44: =SUMIFS(Consultas!$L$2:$L$1000,Consultas!$C$2:$C$1000,$A44,Consultas!$D$2:$D$1000,"<>",Consultas!$G$2:$G$1000,"<>Sí",Consultas!$B$2:$B$1000,">="&IF($B$4="",1,$B$4),Consultas!$B$2:$B$1000,"<="&IF($B$5="",2958465,$B$5),Consultas!$K$2:$K$1000,"Sí") -> 0 | H44: No aplica | I44: =IF(B44=0,"NO CALCULABLE",C44/B44) -> NO CALCULABLE | J44: =IF(C44=0,"NO CALCULABLE",E44/C44) -> NO CALCULABLE | K44: No aplica
A45: No dijo | B45: =COUNTIFS(Consultas!$C$2:$C$1000,$A45,Consultas!$D$2:$D$1000,"<>",Consultas!$G$2:$G$1000,"<>Sí",Consultas!$B$2:$B$1000,">="&IF($B$4="",1,$B$4),Consultas!$B$2:$B$1000,"<="&IF($B$5="",2958465,$B$5)) -> 0 | C45: =COUNTIFS(Consultas!$C$2:$C$1000,$A45,Consultas!$D$2:$D$1000,"<>",Consultas!$G$2:$G$1000,"<>Sí",Consultas!$B$2:$B$1000,">="&IF($B$4="",1,$B$4),Consultas!$B$2:$B$1000,"<="&IF($B$5="",2958465,$B$5),Consultas!$H$2:$H$1000,"Sí") -> 0 | D45: =COUNTIFS(Consultas!$C$2:$C$1000,$A45,Consultas!$D$2:$D$1000,"<>",Consultas!$G$2:$G$1000,"<>Sí",Consultas!$B$2:$B$1000,">="&IF($B$4="",1,$B$4),Consultas!$B$2:$B$1000,"<="&IF($B$5="",2958465,$B$5),Consultas!$I$2:$I$1000,"Sí") -> 0 | E45: =COUNTIFS(Consultas!$C$2:$C$1000,$A45,Consultas!$D$2:$D$1000,"<>",Consultas!$G$2:$G$1000,"<>Sí",Consultas!$B$2:$B$1000,">="&IF($B$4="",1,$B$4),Consultas!$B$2:$B$1000,"<="&IF($B$5="",2958465,$B$5),Consultas!$J$2:$J$1000,"Sí") -> 0 | F45: =COUNTIFS(Consultas!$C$2:$C$1000,$A45,Consultas!$D$2:$D$1000,"<>",Consultas!$G$2:$G$1000,"<>Sí",Consultas!$B$2:$B$1000,">="&IF($B$4="",1,$B$4),Consultas!$B$2:$B$1000,"<="&IF($B$5="",2958465,$B$5),Consultas!$K$2:$K$1000,"Sí") -> 0 | G45: =SUMIFS(Consultas!$L$2:$L$1000,Consultas!$C$2:$C$1000,$A45,Consultas!$D$2:$D$1000,"<>",Consultas!$G$2:$G$1000,"<>Sí",Consultas!$B$2:$B$1000,">="&IF($B$4="",1,$B$4),Consultas!$B$2:$B$1000,"<="&IF($B$5="",2958465,$B$5),Consultas!$K$2:$K$1000,"Sí") -> 0 | H45: No aplica | I45: =IF(B45=0,"NO CALCULABLE",C45/B45) -> NO CALCULABLE | J45: =IF(C45=0,"NO CALCULABLE",E45/C45) -> NO CALCULABLE | K45: No aplica
A46: Total | B46: =SUM(B36:B45) -> 0 | C46: =SUM(C36:C45) -> 0 | D46: =SUM(D36:D45) -> 0 | E46: =SUM(E36:E45) -> 0 | F46: =SUM(F36:F45) -> 0 | G46: =SUM(G36:G45) -> 0 | H46: No aplica | I46: =IF(B46=0,"NO CALCULABLE",C46/B46) -> NO CALCULABLE | J46: =IF(C46=0,"NO CALCULABLE",E46/C46) -> NO CALCULABLE | K46: No aplica
A47: Consultas del periodo con código pero sin canal anotado (no entran en este cuadro) | I47: =$B$16-B46 -> 0
A48: =IF(AND(SUMIF($H$10:$H$13,">0")>0,N($H$42)>0),"Hay pauta escrita en los dos cuadros: confirmá que son anuncios distintos y que ningún gasto está anotado dos veces.","")
A50: Condiciones de la prueba (contestar al revisar)
A51: ¿Algún producto de la prueba estuvo sin stock en algún momento del periodo?
A52: ¿Cambiaron el precio, la oferta o el costo de envío durante el periodo?
A53: ¿GAME1 y GAME2 salieron en el mismo canal y a la misma hora del día?
A54: ¿GAME1 y GAME2 tuvieron la misma inversión en pauta (o ninguna de las dos)?
A55: Lectura | B55: =IF(COUNTA($I$51,$I$52,$I$53,$I$54)<4,"Contestá las cuatro preguntas antes de comparar piezas.",IF(OR($I$51="Sí",$I$52="Sí",$I$53="No",$I$54="No"),"Comparación entre piezas NO VÁLIDA en este periodo: extendé o repetí la prueba con condiciones parejas.","Condiciones parejas declaradas. Con pocas consultas igual no se declara ganador: seguí observando.")) -> Contestá las cuatro preguntas antes de comparar piezas.
A57: Prueba A: GAME1 frente a GAME2 con ventanas iguales
A58: Cada pieza se cuenta desde su fecha de publicación hasta 3 días después, inclusive (aproxima las 72 h del plan con fechas sin hora). Este bloque no usa Desde/Hasta.
A59: El alcance de esta tabla es el de cada pieza leído en Insights el día «Cuenta hasta». Si falta el de una de las dos, la lectura es solo descriptiva.
A60: Pieza | B60: Fecha de publicación · escribir a mano | C60: Cuenta hasta | D60: Consultas únicas | E60: Cualificadas | F60: Cotizaciones | G60: Pedidos confirmados | H60: Cualificadas / consultas | I60: Pedidos / cualificadas | J60: Alcance en su ventana (Insights) · escribir a mano | K60: Cualificadas / alcance
A61: GAME1 | C61: =IF($B61="","Falta fecha",$B61+3) -> Falta fecha | D61: =IF($B61="","",COUNTIFS(Consultas!$D$2:$D$1000,$A61,Consultas!$G$2:$G$1000,"<>Sí",Consultas!$B$2:$B$1000,">="&$B61,Consultas!$B$2:$B$1000,"<="&($B61+3))) | E61: =IF($B61="","",COUNTIFS(Consultas!$D$2:$D$1000,$A61,Consultas!$G$2:$G$1000,"<>Sí",Consultas!$B$2:$B$1000,">="&$B61,Consultas!$B$2:$B$1000,"<="&($B61+3),Consultas!$H$2:$H$1000,"Sí")) | F61: =IF($B61="","",COUNTIFS(Consultas!$D$2:$D$1000,$A61,Consultas!$G$2:$G$1000,"<>Sí",Consultas!$B$2:$B$1000,">="&$B61,Consultas!$B$2:$B$1000,"<="&($B61+3),Consultas!$I$2:$I$1000,"Sí")) | G61: =IF($B61="","",COUNTIFS(Consultas!$D$2:$D$1000,$A61,Consultas!$G$2:$G$1000,"<>Sí",Consultas!$B$2:$B$1000,">="&$B61,Consultas!$B$2:$B$1000,"<="&($B61+3),Consultas!$J$2:$J$1000,"Sí")) | H61: =IF(N(D61)=0,"NO CALCULABLE",E61/D61) -> NO CALCULABLE | I61: =IF(N(E61)=0,"NO CALCULABLE",G61/E61) -> NO CALCULABLE | K61: =IF(OR($B61="",N(J61)=0),"NO CALCULABLE",E61/J61) -> NO CALCULABLE
A62: GAME2 | C62: =IF($B62="","Falta fecha",$B62+3) -> Falta fecha | D62: =IF($B62="","",COUNTIFS(Consultas!$D$2:$D$1000,$A62,Consultas!$G$2:$G$1000,"<>Sí",Consultas!$B$2:$B$1000,">="&$B62,Consultas!$B$2:$B$1000,"<="&($B62+3))) | E62: =IF($B62="","",COUNTIFS(Consultas!$D$2:$D$1000,$A62,Consultas!$G$2:$G$1000,"<>Sí",Consultas!$B$2:$B$1000,">="&$B62,Consultas!$B$2:$B$1000,"<="&($B62+3),Consultas!$H$2:$H$1000,"Sí")) | F62: =IF($B62="","",COUNTIFS(Consultas!$D$2:$D$1000,$A62,Consultas!$G$2:$G$1000,"<>Sí",Consultas!$B$2:$B$1000,">="&$B62,Consultas!$B$2:$B$1000,"<="&($B62+3),Consultas!$I$2:$I$1000,"Sí")) | G62: =IF($B62="","",COUNTIFS(Consultas!$D$2:$D$1000,$A62,Consultas!$G$2:$G$1000,"<>Sí",Consultas!$B$2:$B$1000,">="&$B62,Consultas!$B$2:$B$1000,"<="&($B62+3),Consultas!$J$2:$J$1000,"Sí")) | H62: =IF(N(D62)=0,"NO CALCULABLE",E62/D62) -> NO CALCULABLE | I62: =IF(N(E62)=0,"NO CALCULABLE",G62/E62) -> NO CALCULABLE | K62: =IF(OR($B62="",N(J62)=0),"NO CALCULABLE",E62/J62) -> NO CALCULABLE
A63: GAME2 − GAME1 | D63: =IF(OR($B$61="",$B$62=""),"",D62-D61) | E63: =IF(OR($B$61="",$B$62=""),"",E62-E61) | F63: =IF(OR($B$61="",$B$62=""),"",F62-F61) | G63: =IF(OR($B$61="",$B$62=""),"",G62-G61)
A64: Lectura | B64: =IF(OR($B$61="",$B$62=""),"Escribí las dos fechas de publicación para comparar.",IF(COUNTA($I$51,$I$52,$I$53,$I$54)<4,"Contestá las cuatro preguntas de condiciones antes de comparar.",IF(OR($I$51="Sí",$I$52="Sí",$I$53="No",$I$54="No"),"Comparación NO VÁLIDA: las condiciones no fueron parejas. Repetí la prueba.",IF($E$63=0,"GAME1 y GAME2 tuvieron las mismas consultas cualificadas.","GAME2 tuvo "&ABS($E$63)&" consulta(s) cualificada(s) "&IF($E$63>0,"más","menos")&" que GAME1.")&IF(OR(N($J$61)=0,N($J$62)=0)," Falta el alcance de al menos una pieza: la lectura es solo descriptiva y se comparan volúmenes absolutos junto al alcance conocido."," Las dos piezas tienen alcance: mirá también Cualificadas / alcance.")&" Es una señal exploratoria, no un ganador: no se sabe en qué dirección influyen el día, el orden ni el alcance."))) -> Escribí las dos fechas de publicación para comparar.
A66: Zona de las consultas únicas
A67: Código | B67: GAM | C67: Fuera de GAM | D67: No dijo | E67: Sin dato
A68: GAME1 | B68: =COUNTIFS(Consultas!$D$2:$D$1000,$A68,Consultas!$G$2:$G$1000,"<>Sí",Consultas!$B$2:$B$1000,">="&IF($B$4="",1,$B$4),Consultas!$B$2:$B$1000,"<="&IF($B$5="",2958465,$B$5),Consultas!$F$2:$F$1000,"GAM") -> 0 | C68: =COUNTIFS(Consultas!$D$2:$D$1000,$A68,Consultas!$G$2:$G$1000,"<>Sí",Consultas!$B$2:$B$1000,">="&IF($B$4="",1,$B$4),Consultas!$B$2:$B$1000,"<="&IF($B$5="",2958465,$B$5),Consultas!$F$2:$F$1000,"Fuera de GAM") -> 0 | D68: =COUNTIFS(Consultas!$D$2:$D$1000,$A68,Consultas!$G$2:$G$1000,"<>Sí",Consultas!$B$2:$B$1000,">="&IF($B$4="",1,$B$4),Consultas!$B$2:$B$1000,"<="&IF($B$5="",2958465,$B$5),Consultas!$F$2:$F$1000,"No dijo") -> 0 | E68: =$B$10-SUM(B68:D68) -> 0
A69: GAME2 | B69: =COUNTIFS(Consultas!$D$2:$D$1000,$A69,Consultas!$G$2:$G$1000,"<>Sí",Consultas!$B$2:$B$1000,">="&IF($B$4="",1,$B$4),Consultas!$B$2:$B$1000,"<="&IF($B$5="",2958465,$B$5),Consultas!$F$2:$F$1000,"GAM") -> 0 | C69: =COUNTIFS(Consultas!$D$2:$D$1000,$A69,Consultas!$G$2:$G$1000,"<>Sí",Consultas!$B$2:$B$1000,">="&IF($B$4="",1,$B$4),Consultas!$B$2:$B$1000,"<="&IF($B$5="",2958465,$B$5),Consultas!$F$2:$F$1000,"Fuera de GAM") -> 0 | D69: =COUNTIFS(Consultas!$D$2:$D$1000,$A69,Consultas!$G$2:$G$1000,"<>Sí",Consultas!$B$2:$B$1000,">="&IF($B$4="",1,$B$4),Consultas!$B$2:$B$1000,"<="&IF($B$5="",2958465,$B$5),Consultas!$F$2:$F$1000,"No dijo") -> 0 | E69: =$B$11-SUM(B69:D69) -> 0
A70: RETRO1 | B70: =COUNTIFS(Consultas!$D$2:$D$1000,$A70,Consultas!$G$2:$G$1000,"<>Sí",Consultas!$B$2:$B$1000,">="&IF($B$4="",1,$B$4),Consultas!$B$2:$B$1000,"<="&IF($B$5="",2958465,$B$5),Consultas!$F$2:$F$1000,"GAM") -> 0 | C70: =COUNTIFS(Consultas!$D$2:$D$1000,$A70,Consultas!$G$2:$G$1000,"<>Sí",Consultas!$B$2:$B$1000,">="&IF($B$4="",1,$B$4),Consultas!$B$2:$B$1000,"<="&IF($B$5="",2958465,$B$5),Consultas!$F$2:$F$1000,"Fuera de GAM") -> 0 | D70: =COUNTIFS(Consultas!$D$2:$D$1000,$A70,Consultas!$G$2:$G$1000,"<>Sí",Consultas!$B$2:$B$1000,">="&IF($B$4="",1,$B$4),Consultas!$B$2:$B$1000,"<="&IF($B$5="",2958465,$B$5),Consultas!$F$2:$F$1000,"No dijo") -> 0 | E70: =$B$12-SUM(B70:D70) -> 0
A71: RGB1 | B71: =COUNTIFS(Consultas!$D$2:$D$1000,$A71,Consultas!$G$2:$G$1000,"<>Sí",Consultas!$B$2:$B$1000,">="&IF($B$4="",1,$B$4),Consultas!$B$2:$B$1000,"<="&IF($B$5="",2958465,$B$5),Consultas!$F$2:$F$1000,"GAM") -> 0 | C71: =COUNTIFS(Consultas!$D$2:$D$1000,$A71,Consultas!$G$2:$G$1000,"<>Sí",Consultas!$B$2:$B$1000,">="&IF($B$4="",1,$B$4),Consultas!$B$2:$B$1000,"<="&IF($B$5="",2958465,$B$5),Consultas!$F$2:$F$1000,"Fuera de GAM") -> 0 | D71: =COUNTIFS(Consultas!$D$2:$D$1000,$A71,Consultas!$G$2:$G$1000,"<>Sí",Consultas!$B$2:$B$1000,">="&IF($B$4="",1,$B$4),Consultas!$B$2:$B$1000,"<="&IF($B$5="",2958465,$B$5),Consultas!$F$2:$F$1000,"No dijo") -> 0 | E71: =$B$13-SUM(B71:D71) -> 0
A72: OTRO | B72: =COUNTIFS(Consultas!$D$2:$D$1000,$A72,Consultas!$G$2:$G$1000,"<>Sí",Consultas!$B$2:$B$1000,">="&IF($B$4="",1,$B$4),Consultas!$B$2:$B$1000,"<="&IF($B$5="",2958465,$B$5),Consultas!$F$2:$F$1000,"GAM") -> 0 | C72: =COUNTIFS(Consultas!$D$2:$D$1000,$A72,Consultas!$G$2:$G$1000,"<>Sí",Consultas!$B$2:$B$1000,">="&IF($B$4="",1,$B$4),Consultas!$B$2:$B$1000,"<="&IF($B$5="",2958465,$B$5),Consultas!$F$2:$F$1000,"Fuera de GAM") -> 0 | D72: =COUNTIFS(Consultas!$D$2:$D$1000,$A72,Consultas!$G$2:$G$1000,"<>Sí",Consultas!$B$2:$B$1000,">="&IF($B$4="",1,$B$4),Consultas!$B$2:$B$1000,"<="&IF($B$5="",2958465,$B$5),Consultas!$F$2:$F$1000,"No dijo") -> 0 | E72: =$B$14-SUM(B72:D72) -> 0
A73: SIN CODIGO | B73: =COUNTIFS(Consultas!$D$2:$D$1000,$A73,Consultas!$G$2:$G$1000,"<>Sí",Consultas!$B$2:$B$1000,">="&IF($B$4="",1,$B$4),Consultas!$B$2:$B$1000,"<="&IF($B$5="",2958465,$B$5),Consultas!$F$2:$F$1000,"GAM") -> 0 | C73: =COUNTIFS(Consultas!$D$2:$D$1000,$A73,Consultas!$G$2:$G$1000,"<>Sí",Consultas!$B$2:$B$1000,">="&IF($B$4="",1,$B$4),Consultas!$B$2:$B$1000,"<="&IF($B$5="",2958465,$B$5),Consultas!$F$2:$F$1000,"Fuera de GAM") -> 0 | D73: =COUNTIFS(Consultas!$D$2:$D$1000,$A73,Consultas!$G$2:$G$1000,"<>Sí",Consultas!$B$2:$B$1000,">="&IF($B$4="",1,$B$4),Consultas!$B$2:$B$1000,"<="&IF($B$5="",2958465,$B$5),Consultas!$F$2:$F$1000,"No dijo") -> 0 | E73: =$B$15-SUM(B73:D73) -> 0
A74: Total | B74: =SUM(B68:B73) -> 0 | C74: =SUM(C68:C73) -> 0 | D74: =SUM(D68:D73) -> 0 | E74: =SUM(E68:E73) -> 0
A76: Objeción principal de las consultas únicas
A77: Código | B77: Precio | C77: Compatibilidad | D77: Envío | E77: Garantía | F77: Confianza | G77: Stock | H77: Otra | I77: Sin objeción anotada
A78: GAME1 | B78: =COUNTIFS(Consultas!$D$2:$D$1000,$A78,Consultas!$G$2:$G$1000,"<>Sí",Consultas!$B$2:$B$1000,">="&IF($B$4="",1,$B$4),Consultas!$B$2:$B$1000,"<="&IF($B$5="",2958465,$B$5),Consultas!$N$2:$N$1000,"Precio") -> 0 | C78: =COUNTIFS(Consultas!$D$2:$D$1000,$A78,Consultas!$G$2:$G$1000,"<>Sí",Consultas!$B$2:$B$1000,">="&IF($B$4="",1,$B$4),Consultas!$B$2:$B$1000,"<="&IF($B$5="",2958465,$B$5),Consultas!$N$2:$N$1000,"Compatibilidad") -> 0 | D78: =COUNTIFS(Consultas!$D$2:$D$1000,$A78,Consultas!$G$2:$G$1000,"<>Sí",Consultas!$B$2:$B$1000,">="&IF($B$4="",1,$B$4),Consultas!$B$2:$B$1000,"<="&IF($B$5="",2958465,$B$5),Consultas!$N$2:$N$1000,"Envío") -> 0 | E78: =COUNTIFS(Consultas!$D$2:$D$1000,$A78,Consultas!$G$2:$G$1000,"<>Sí",Consultas!$B$2:$B$1000,">="&IF($B$4="",1,$B$4),Consultas!$B$2:$B$1000,"<="&IF($B$5="",2958465,$B$5),Consultas!$N$2:$N$1000,"Garantía") -> 0 | F78: =COUNTIFS(Consultas!$D$2:$D$1000,$A78,Consultas!$G$2:$G$1000,"<>Sí",Consultas!$B$2:$B$1000,">="&IF($B$4="",1,$B$4),Consultas!$B$2:$B$1000,"<="&IF($B$5="",2958465,$B$5),Consultas!$N$2:$N$1000,"Confianza") -> 0 | G78: =COUNTIFS(Consultas!$D$2:$D$1000,$A78,Consultas!$G$2:$G$1000,"<>Sí",Consultas!$B$2:$B$1000,">="&IF($B$4="",1,$B$4),Consultas!$B$2:$B$1000,"<="&IF($B$5="",2958465,$B$5),Consultas!$N$2:$N$1000,"Stock") -> 0 | H78: =COUNTIFS(Consultas!$D$2:$D$1000,$A78,Consultas!$G$2:$G$1000,"<>Sí",Consultas!$B$2:$B$1000,">="&IF($B$4="",1,$B$4),Consultas!$B$2:$B$1000,"<="&IF($B$5="",2958465,$B$5),Consultas!$N$2:$N$1000,"Otra") -> 0 | I78: =$B$10-SUM(B78:H78) -> 0
A79: GAME2 | B79: =COUNTIFS(Consultas!$D$2:$D$1000,$A79,Consultas!$G$2:$G$1000,"<>Sí",Consultas!$B$2:$B$1000,">="&IF($B$4="",1,$B$4),Consultas!$B$2:$B$1000,"<="&IF($B$5="",2958465,$B$5),Consultas!$N$2:$N$1000,"Precio") -> 0 | C79: =COUNTIFS(Consultas!$D$2:$D$1000,$A79,Consultas!$G$2:$G$1000,"<>Sí",Consultas!$B$2:$B$1000,">="&IF($B$4="",1,$B$4),Consultas!$B$2:$B$1000,"<="&IF($B$5="",2958465,$B$5),Consultas!$N$2:$N$1000,"Compatibilidad") -> 0 | D79: =COUNTIFS(Consultas!$D$2:$D$1000,$A79,Consultas!$G$2:$G$1000,"<>Sí",Consultas!$B$2:$B$1000,">="&IF($B$4="",1,$B$4),Consultas!$B$2:$B$1000,"<="&IF($B$5="",2958465,$B$5),Consultas!$N$2:$N$1000,"Envío") -> 0 | E79: =COUNTIFS(Consultas!$D$2:$D$1000,$A79,Consultas!$G$2:$G$1000,"<>Sí",Consultas!$B$2:$B$1000,">="&IF($B$4="",1,$B$4),Consultas!$B$2:$B$1000,"<="&IF($B$5="",2958465,$B$5),Consultas!$N$2:$N$1000,"Garantía") -> 0 | F79: =COUNTIFS(Consultas!$D$2:$D$1000,$A79,Consultas!$G$2:$G$1000,"<>Sí",Consultas!$B$2:$B$1000,">="&IF($B$4="",1,$B$4),Consultas!$B$2:$B$1000,"<="&IF($B$5="",2958465,$B$5),Consultas!$N$2:$N$1000,"Confianza") -> 0 | G79: =COUNTIFS(Consultas!$D$2:$D$1000,$A79,Consultas!$G$2:$G$1000,"<>Sí",Consultas!$B$2:$B$1000,">="&IF($B$4="",1,$B$4),Consultas!$B$2:$B$1000,"<="&IF($B$5="",2958465,$B$5),Consultas!$N$2:$N$1000,"Stock") -> 0 | H79: =COUNTIFS(Consultas!$D$2:$D$1000,$A79,Consultas!$G$2:$G$1000,"<>Sí",Consultas!$B$2:$B$1000,">="&IF($B$4="",1,$B$4),Consultas!$B$2:$B$1000,"<="&IF($B$5="",2958465,$B$5),Consultas!$N$2:$N$1000,"Otra") -> 0 | I79: =$B$11-SUM(B79:H79) -> 0
A80: RETRO1 | B80: =COUNTIFS(Consultas!$D$2:$D$1000,$A80,Consultas!$G$2:$G$1000,"<>Sí",Consultas!$B$2:$B$1000,">="&IF($B$4="",1,$B$4),Consultas!$B$2:$B$1000,"<="&IF($B$5="",2958465,$B$5),Consultas!$N$2:$N$1000,"Precio") -> 0 | C80: =COUNTIFS(Consultas!$D$2:$D$1000,$A80,Consultas!$G$2:$G$1000,"<>Sí",Consultas!$B$2:$B$1000,">="&IF($B$4="",1,$B$4),Consultas!$B$2:$B$1000,"<="&IF($B$5="",2958465,$B$5),Consultas!$N$2:$N$1000,"Compatibilidad") -> 0 | D80: =COUNTIFS(Consultas!$D$2:$D$1000,$A80,Consultas!$G$2:$G$1000,"<>Sí",Consultas!$B$2:$B$1000,">="&IF($B$4="",1,$B$4),Consultas!$B$2:$B$1000,"<="&IF($B$5="",2958465,$B$5),Consultas!$N$2:$N$1000,"Envío") -> 0 | E80: =COUNTIFS(Consultas!$D$2:$D$1000,$A80,Consultas!$G$2:$G$1000,"<>Sí",Consultas!$B$2:$B$1000,">="&IF($B$4="",1,$B$4),Consultas!$B$2:$B$1000,"<="&IF($B$5="",2958465,$B$5),Consultas!$N$2:$N$1000,"Garantía") -> 0 | F80: =COUNTIFS(Consultas!$D$2:$D$1000,$A80,Consultas!$G$2:$G$1000,"<>Sí",Consultas!$B$2:$B$1000,">="&IF($B$4="",1,$B$4),Consultas!$B$2:$B$1000,"<="&IF($B$5="",2958465,$B$5),Consultas!$N$2:$N$1000,"Confianza") -> 0 | G80: =COUNTIFS(Consultas!$D$2:$D$1000,$A80,Consultas!$G$2:$G$1000,"<>Sí",Consultas!$B$2:$B$1000,">="&IF($B$4="",1,$B$4),Consultas!$B$2:$B$1000,"<="&IF($B$5="",2958465,$B$5),Consultas!$N$2:$N$1000,"Stock") -> 0 | H80: =COUNTIFS(Consultas!$D$2:$D$1000,$A80,Consultas!$G$2:$G$1000,"<>Sí",Consultas!$B$2:$B$1000,">="&IF($B$4="",1,$B$4),Consultas!$B$2:$B$1000,"<="&IF($B$5="",2958465,$B$5),Consultas!$N$2:$N$1000,"Otra") -> 0 | I80: =$B$12-SUM(B80:H80) -> 0
A81: RGB1 | B81: =COUNTIFS(Consultas!$D$2:$D$1000,$A81,Consultas!$G$2:$G$1000,"<>Sí",Consultas!$B$2:$B$1000,">="&IF($B$4="",1,$B$4),Consultas!$B$2:$B$1000,"<="&IF($B$5="",2958465,$B$5),Consultas!$N$2:$N$1000,"Precio") -> 0 | C81: =COUNTIFS(Consultas!$D$2:$D$1000,$A81,Consultas!$G$2:$G$1000,"<>Sí",Consultas!$B$2:$B$1000,">="&IF($B$4="",1,$B$4),Consultas!$B$2:$B$1000,"<="&IF($B$5="",2958465,$B$5),Consultas!$N$2:$N$1000,"Compatibilidad") -> 0 | D81: =COUNTIFS(Consultas!$D$2:$D$1000,$A81,Consultas!$G$2:$G$1000,"<>Sí",Consultas!$B$2:$B$1000,">="&IF($B$4="",1,$B$4),Consultas!$B$2:$B$1000,"<="&IF($B$5="",2958465,$B$5),Consultas!$N$2:$N$1000,"Envío") -> 0 | E81: =COUNTIFS(Consultas!$D$2:$D$1000,$A81,Consultas!$G$2:$G$1000,"<>Sí",Consultas!$B$2:$B$1000,">="&IF($B$4="",1,$B$4),Consultas!$B$2:$B$1000,"<="&IF($B$5="",2958465,$B$5),Consultas!$N$2:$N$1000,"Garantía") -> 0 | F81: =COUNTIFS(Consultas!$D$2:$D$1000,$A81,Consultas!$G$2:$G$1000,"<>Sí",Consultas!$B$2:$B$1000,">="&IF($B$4="",1,$B$4),Consultas!$B$2:$B$1000,"<="&IF($B$5="",2958465,$B$5),Consultas!$N$2:$N$1000,"Confianza") -> 0 | G81: =COUNTIFS(Consultas!$D$2:$D$1000,$A81,Consultas!$G$2:$G$1000,"<>Sí",Consultas!$B$2:$B$1000,">="&IF($B$4="",1,$B$4),Consultas!$B$2:$B$1000,"<="&IF($B$5="",2958465,$B$5),Consultas!$N$2:$N$1000,"Stock") -> 0 | H81: =COUNTIFS(Consultas!$D$2:$D$1000,$A81,Consultas!$G$2:$G$1000,"<>Sí",Consultas!$B$2:$B$1000,">="&IF($B$4="",1,$B$4),Consultas!$B$2:$B$1000,"<="&IF($B$5="",2958465,$B$5),Consultas!$N$2:$N$1000,"Otra") -> 0 | I81: =$B$13-SUM(B81:H81) -> 0
A82: OTRO | B82: =COUNTIFS(Consultas!$D$2:$D$1000,$A82,Consultas!$G$2:$G$1000,"<>Sí",Consultas!$B$2:$B$1000,">="&IF($B$4="",1,$B$4),Consultas!$B$2:$B$1000,"<="&IF($B$5="",2958465,$B$5),Consultas!$N$2:$N$1000,"Precio") -> 0 | C82: =COUNTIFS(Consultas!$D$2:$D$1000,$A82,Consultas!$G$2:$G$1000,"<>Sí",Consultas!$B$2:$B$1000,">="&IF($B$4="",1,$B$4),Consultas!$B$2:$B$1000,"<="&IF($B$5="",2958465,$B$5),Consultas!$N$2:$N$1000,"Compatibilidad") -> 0 | D82: =COUNTIFS(Consultas!$D$2:$D$1000,$A82,Consultas!$G$2:$G$1000,"<>Sí",Consultas!$B$2:$B$1000,">="&IF($B$4="",1,$B$4),Consultas!$B$2:$B$1000,"<="&IF($B$5="",2958465,$B$5),Consultas!$N$2:$N$1000,"Envío") -> 0 | E82: =COUNTIFS(Consultas!$D$2:$D$1000,$A82,Consultas!$G$2:$G$1000,"<>Sí",Consultas!$B$2:$B$1000,">="&IF($B$4="",1,$B$4),Consultas!$B$2:$B$1000,"<="&IF($B$5="",2958465,$B$5),Consultas!$N$2:$N$1000,"Garantía") -> 0 | F82: =COUNTIFS(Consultas!$D$2:$D$1000,$A82,Consultas!$G$2:$G$1000,"<>Sí",Consultas!$B$2:$B$1000,">="&IF($B$4="",1,$B$4),Consultas!$B$2:$B$1000,"<="&IF($B$5="",2958465,$B$5),Consultas!$N$2:$N$1000,"Confianza") -> 0 | G82: =COUNTIFS(Consultas!$D$2:$D$1000,$A82,Consultas!$G$2:$G$1000,"<>Sí",Consultas!$B$2:$B$1000,">="&IF($B$4="",1,$B$4),Consultas!$B$2:$B$1000,"<="&IF($B$5="",2958465,$B$5),Consultas!$N$2:$N$1000,"Stock") -> 0 | H82: =COUNTIFS(Consultas!$D$2:$D$1000,$A82,Consultas!$G$2:$G$1000,"<>Sí",Consultas!$B$2:$B$1000,">="&IF($B$4="",1,$B$4),Consultas!$B$2:$B$1000,"<="&IF($B$5="",2958465,$B$5),Consultas!$N$2:$N$1000,"Otra") -> 0 | I82: =$B$14-SUM(B82:H82) -> 0
A83: SIN CODIGO | B83: =COUNTIFS(Consultas!$D$2:$D$1000,$A83,Consultas!$G$2:$G$1000,"<>Sí",Consultas!$B$2:$B$1000,">="&IF($B$4="",1,$B$4),Consultas!$B$2:$B$1000,"<="&IF($B$5="",2958465,$B$5),Consultas!$N$2:$N$1000,"Precio") -> 0 | C83: =COUNTIFS(Consultas!$D$2:$D$1000,$A83,Consultas!$G$2:$G$1000,"<>Sí",Consultas!$B$2:$B$1000,">="&IF($B$4="",1,$B$4),Consultas!$B$2:$B$1000,"<="&IF($B$5="",2958465,$B$5),Consultas!$N$2:$N$1000,"Compatibilidad") -> 0 | D83: =COUNTIFS(Consultas!$D$2:$D$1000,$A83,Consultas!$G$2:$G$1000,"<>Sí",Consultas!$B$2:$B$1000,">="&IF($B$4="",1,$B$4),Consultas!$B$2:$B$1000,"<="&IF($B$5="",2958465,$B$5),Consultas!$N$2:$N$1000,"Envío") -> 0 | E83: =COUNTIFS(Consultas!$D$2:$D$1000,$A83,Consultas!$G$2:$G$1000,"<>Sí",Consultas!$B$2:$B$1000,">="&IF($B$4="",1,$B$4),Consultas!$B$2:$B$1000,"<="&IF($B$5="",2958465,$B$5),Consultas!$N$2:$N$1000,"Garantía") -> 0 | F83: =COUNTIFS(Consultas!$D$2:$D$1000,$A83,Consultas!$G$2:$G$1000,"<>Sí",Consultas!$B$2:$B$1000,">="&IF($B$4="",1,$B$4),Consultas!$B$2:$B$1000,"<="&IF($B$5="",2958465,$B$5),Consultas!$N$2:$N$1000,"Confianza") -> 0 | G83: =COUNTIFS(Consultas!$D$2:$D$1000,$A83,Consultas!$G$2:$G$1000,"<>Sí",Consultas!$B$2:$B$1000,">="&IF($B$4="",1,$B$4),Consultas!$B$2:$B$1000,"<="&IF($B$5="",2958465,$B$5),Consultas!$N$2:$N$1000,"Stock") -> 0 | H83: =COUNTIFS(Consultas!$D$2:$D$1000,$A83,Consultas!$G$2:$G$1000,"<>Sí",Consultas!$B$2:$B$1000,">="&IF($B$4="",1,$B$4),Consultas!$B$2:$B$1000,"<="&IF($B$5="",2958465,$B$5),Consultas!$N$2:$N$1000,"Otra") -> 0 | I83: =$B$15-SUM(B83:H83) -> 0
A84: Total | B84: =SUM(B78:B83) -> 0 | C84: =SUM(C78:C83) -> 0 | D84: =SUM(D78:D83) -> 0 | E84: =SUM(E78:E83) -> 0 | F84: =SUM(F78:F83) -> 0 | G84: =SUM(G78:G83) -> 0 | H84: =SUM(H78:H83) -> 0 | I84: =SUM(I78:I83) -> 0
A86: Tiempo hasta la primera respuesta (consultas únicas)
A87: Código | B87: Consultas con minutos anotados | C87: Minutos sumados | D87: Promedio de minutos
A88: GAME1 | B88: =COUNTIFS(Consultas!$D$2:$D$1000,$A88,Consultas!$G$2:$G$1000,"<>Sí",Consultas!$B$2:$B$1000,">="&IF($B$4="",1,$B$4),Consultas!$B$2:$B$1000,"<="&IF($B$5="",2958465,$B$5),Consultas!$M$2:$M$1000,">=0") -> 0 | C88: =SUMIFS(Consultas!$M$2:$M$1000,Consultas!$D$2:$D$1000,$A88,Consultas!$G$2:$G$1000,"<>Sí",Consultas!$B$2:$B$1000,">="&IF($B$4="",1,$B$4),Consultas!$B$2:$B$1000,"<="&IF($B$5="",2958465,$B$5),Consultas!$M$2:$M$1000,">=0") -> 0 | D88: =IF(B88=0,"NO CALCULABLE",C88/B88) -> NO CALCULABLE
A89: GAME2 | B89: =COUNTIFS(Consultas!$D$2:$D$1000,$A89,Consultas!$G$2:$G$1000,"<>Sí",Consultas!$B$2:$B$1000,">="&IF($B$4="",1,$B$4),Consultas!$B$2:$B$1000,"<="&IF($B$5="",2958465,$B$5),Consultas!$M$2:$M$1000,">=0") -> 0 | C89: =SUMIFS(Consultas!$M$2:$M$1000,Consultas!$D$2:$D$1000,$A89,Consultas!$G$2:$G$1000,"<>Sí",Consultas!$B$2:$B$1000,">="&IF($B$4="",1,$B$4),Consultas!$B$2:$B$1000,"<="&IF($B$5="",2958465,$B$5),Consultas!$M$2:$M$1000,">=0") -> 0 | D89: =IF(B89=0,"NO CALCULABLE",C89/B89) -> NO CALCULABLE
A90: RETRO1 | B90: =COUNTIFS(Consultas!$D$2:$D$1000,$A90,Consultas!$G$2:$G$1000,"<>Sí",Consultas!$B$2:$B$1000,">="&IF($B$4="",1,$B$4),Consultas!$B$2:$B$1000,"<="&IF($B$5="",2958465,$B$5),Consultas!$M$2:$M$1000,">=0") -> 0 | C90: =SUMIFS(Consultas!$M$2:$M$1000,Consultas!$D$2:$D$1000,$A90,Consultas!$G$2:$G$1000,"<>Sí",Consultas!$B$2:$B$1000,">="&IF($B$4="",1,$B$4),Consultas!$B$2:$B$1000,"<="&IF($B$5="",2958465,$B$5),Consultas!$M$2:$M$1000,">=0") -> 0 | D90: =IF(B90=0,"NO CALCULABLE",C90/B90) -> NO CALCULABLE
A91: RGB1 | B91: =COUNTIFS(Consultas!$D$2:$D$1000,$A91,Consultas!$G$2:$G$1000,"<>Sí",Consultas!$B$2:$B$1000,">="&IF($B$4="",1,$B$4),Consultas!$B$2:$B$1000,"<="&IF($B$5="",2958465,$B$5),Consultas!$M$2:$M$1000,">=0") -> 0 | C91: =SUMIFS(Consultas!$M$2:$M$1000,Consultas!$D$2:$D$1000,$A91,Consultas!$G$2:$G$1000,"<>Sí",Consultas!$B$2:$B$1000,">="&IF($B$4="",1,$B$4),Consultas!$B$2:$B$1000,"<="&IF($B$5="",2958465,$B$5),Consultas!$M$2:$M$1000,">=0") -> 0 | D91: =IF(B91=0,"NO CALCULABLE",C91/B91) -> NO CALCULABLE
A92: OTRO | B92: =COUNTIFS(Consultas!$D$2:$D$1000,$A92,Consultas!$G$2:$G$1000,"<>Sí",Consultas!$B$2:$B$1000,">="&IF($B$4="",1,$B$4),Consultas!$B$2:$B$1000,"<="&IF($B$5="",2958465,$B$5),Consultas!$M$2:$M$1000,">=0") -> 0 | C92: =SUMIFS(Consultas!$M$2:$M$1000,Consultas!$D$2:$D$1000,$A92,Consultas!$G$2:$G$1000,"<>Sí",Consultas!$B$2:$B$1000,">="&IF($B$4="",1,$B$4),Consultas!$B$2:$B$1000,"<="&IF($B$5="",2958465,$B$5),Consultas!$M$2:$M$1000,">=0") -> 0 | D92: =IF(B92=0,"NO CALCULABLE",C92/B92) -> NO CALCULABLE
A93: SIN CODIGO | B93: =COUNTIFS(Consultas!$D$2:$D$1000,$A93,Consultas!$G$2:$G$1000,"<>Sí",Consultas!$B$2:$B$1000,">="&IF($B$4="",1,$B$4),Consultas!$B$2:$B$1000,"<="&IF($B$5="",2958465,$B$5),Consultas!$M$2:$M$1000,">=0") -> 0 | C93: =SUMIFS(Consultas!$M$2:$M$1000,Consultas!$D$2:$D$1000,$A93,Consultas!$G$2:$G$1000,"<>Sí",Consultas!$B$2:$B$1000,">="&IF($B$4="",1,$B$4),Consultas!$B$2:$B$1000,"<="&IF($B$5="",2958465,$B$5),Consultas!$M$2:$M$1000,">=0") -> 0 | D93: =IF(B93=0,"NO CALCULABLE",C93/B93) -> NO CALCULABLE
A94: Total | B94: =SUM(B88:B93) -> 0 | C94: =SUM(C88:C93) -> 0 | D94: =IF(B94=0,"NO CALCULABLE",C94/B94) -> NO CALCULABLE
A95: Antes de prometer un tiempo de respuesta, medilo aquí. Un promedio alto puede venir de mensajes de noche: revisá también el horario.
A97: Control del registro (todas las filas, sin filtro de fechas)
A98: Filas con fecha pero sin código de pieza | I98: =SUMPRODUCT((LEN(Consultas!$B$2:$B$1000)>0)*(LEN(Consultas!$D$2:$D$1000)=0)) -> 0
A99: Filas con código pero sin fecha (no entran al resumen) | I99: =SUMPRODUCT((LEN(Consultas!$D$2:$D$1000)>0)*(LEN(Consultas!$B$2:$B$1000)=0)) -> 0
A100: Cualificada = Sí sin zona GAM o Fuera de GAM | I100: =SUMPRODUCT((Consultas!$H$2:$H$1000="Sí")*(Consultas!$F$2:$F$1000<>"GAM")*(Consultas!$F$2:$F$1000<>"Fuera de GAM")) -> 0
A101: Pedido confirmado = Sí sin Cualificada = Sí | I101: =SUMPRODUCT((Consultas!$J$2:$J$1000="Sí")*(Consultas!$H$2:$H$1000<>"Sí")) -> 0
A102: Cobrado = Sí sin Pedido confirmado = Sí | I102: =SUMPRODUCT((Consultas!$K$2:$K$1000="Sí")*(Consultas!$J$2:$J$1000<>"Sí")) -> 0
A103: Cobrado = Sí sin monto | I103: =SUMPRODUCT((Consultas!$K$2:$K$1000="Sí")*(LEN(Consultas!$L$2:$L$1000)=0)) -> 0
A104: Monto anotado sin Cobrado = Sí | I104: =SUMPRODUCT((LEN(Consultas!$L$2:$L$1000)>0)*(Consultas!$K$2:$K$1000<>"Sí")) -> 0
A105: Filas con código pero sin canal de origen | I105: =SUMPRODUCT((LEN(Consultas!$D$2:$D$1000)>0)*(LEN(Consultas!$C$2:$C$1000)=0)) -> 0
A106: Consultas marcadas como repetidas (no se cuentan en ningún total) | I106: =COUNTIF(Consultas!$G$2:$G$1000,"Sí") -> 0
